biopartitioner
tests
