Metadata-Version: 2.1
Name: biopartitioner
Version: 0.1.14
Summary: UNKNOWN
Home-page: https://github.com/david30907d/bio-partitioner
Author: davidtnfsh
Author-email: davidtnfsh@gmail.com
License: Apache License 2.0
Keywords: bioinformatics partition
Platform: UNKNOWN
Classifier: Development Status :: 4 - Beta
Classifier: Intended Audience :: Developers
Classifier: Topic :: Software Development :: Build Tools
Classifier: License :: OSI Approved :: Apache Software License
Classifier: Programming Language :: Python :: 3
Classifier: Programming Language :: Python :: 3.4
Classifier: Programming Language :: Python :: 3.5
Classifier: Programming Language :: Python :: 3.6
Provides-Extra: dev
